Workbook

Sheet Panel
E2: Panel de control
E3: Resumen del banco. Todo se calcula solo con lo que cargues en las otras hojas.
B6: Landings registradas | E6: Landings dejadas (+600 productos)
B7: =COUNTIF(Landings!$D$7:$D$306,"?*") -> 1 | E7: =COUNTIF(Landings!$L$7:$L$306,"Dejada") -> 0
B9: Landings analizando | E9: Productos revisados
B10: =COUNTIF(Landings!$L$7:$L$306,"Analizando") -> 1 | E10: =COUNTIF(Productos!$D$7:$D$406,"?*") -> 1
B12: Productos de -10 meses | E12: Productos en Dropi
B13: =COUNTIF(Productos!$I$7:$I$406,"Sí") -> 1 | E13: =COUNTIF(Productos!$J$7:$J$406,"Sí") -> 1
B15: Competidores registrados | E15: Competidores que sí cuentan
B16: =COUNTIF(Competencia!$C$7:$C$606,"?*") -> 1 | E16: =COUNTIF(Competencia!$G$7:$G$606,"Sí") -> 1
B18: Competidores que no cuentan | E18: Finalistas en VALIDAR
B19: =COUNTIF(Competencia!$G$7:$G$606,"No") -> 0 | E19: =COUNTIF(Finalistas!$M$7:$M$46,"VALIDAR") -> 0
B21: Finalistas en OBSERVAR | E21: Finalistas descartados
B22: =COUNTIF(Finalistas!$M$7:$M$46,"OBSERVAR") -> 0 | E22: =COUNTIF(Finalistas!$M$7:$M$46,"DESCARTAR") -> 1
B25: Este archivo es un modelo vacío: borra las filas marcadas como ejemplo antes de empezar.

Sheet Landings
E2: Banco de landings ganadoras
E3: Tiendas con más de 600 productos y productos de menos de 10 meses. Una fila por landing.
B6: ID | C6: Fecha | D6: Landing / tienda (URL) | E6: País | F6: N.º productos tienda | G6: ¿Más de 600? | H6: Dolor / nicho | I6: Anuncio (enlace Biblioteca) | J6: Impresiones | K6: Activo desde | L6: Estado | M6: Productos revisados en PPSPY | N6: Notas
B7: =IF(D7="","","L-"&TEXT(ROW()-6,"000")) -> L-001 | C7: 46296 | D7: tienda-ejemplo.com (EJEMPLO, borrar) | E7: Estados Unidos | F7: 850 | G7: =IF(F7="","",IF(F7>600,"Sí","No")) -> Sí | H7: Dolor de espalda | I7: https://www.facebook.com/ads/library/?id=0 | J7: 120000 | K7: 46249 | L7: Analizando | M7: 20 | N7: Fila de ejemplo
B8: =IF(D8="","","L-"&TEXT(ROW()-6,"000")) | G8: =IF(F8="","",IF(F8>600,"Sí","No"))
B9: =IF(D9="","","L-"&TEXT(ROW()-6,"000")) | G9: =IF(F9="","",IF(F9>600,"Sí","No"))
B10: =IF(D10="","","L-"&TEXT(ROW()-6,"000")) | G10: =IF(F10="","",IF(F10>600,"Sí","No"))
B11: =IF(D11="","","L-"&TEXT(ROW()-6,"000")) | G11: =IF(F11="","",IF(F11>600,"Sí","No"))
B12: =IF(D12="","","L-"&TEXT(ROW()-6,"000")) | G12: =IF(F12="","",IF(F12>600,"Sí","No"))
B13: =IF(D13="","","L-"&TEXT(ROW()-6,"000")) | G13: =IF(F13="","",IF(F13>600,"Sí","No"))
B14: =IF(D14="","","L-"&TEXT(ROW()-6,"000")) | G14: =IF(F14="","",IF(F14>600,"Sí","No"))
B15: =IF(D15="","","L-"&TEXT(ROW()-6,"000")) | G15: =IF(F15="","",IF(F15>600,"Sí","No"))
B16: =IF(D16="","","L-"&TEXT(ROW()-6,"000")) | G16: =IF(F16="","",IF(F16>600,"Sí","No"))
B17: =IF(D17="","","L-"&TEXT(ROW()-6,"000")) | G17: =IF(F17="","",IF(F17>600,"Sí","No"))
B18: =IF(D18="","","L-"&TEXT(ROW()-6,"000")) | G18: =IF(F18="","",IF(F18>600,"Sí","No"))
B19: =IF(D19="","","L-"&TEXT(ROW()-6,"000")) | G19: =IF(F19="","",IF(F19>600,"Sí","No"))
... B306: =IF(D306="","","L-"&TEXT(ROW()-6,"000")) | G306: =IF(F306="","",IF(F306>600,"Sí","No"))

Sheet Productos
E2: Best winners por landing (PPSPY)
E3: Unos 20 productos por landing. Al final quedan uno o dos que pasan los filtros.
B6: ID | C6: Landing (ID) | D6: Producto | E6: Enlace producto / anuncio | F6: Precio venta (USD) | G6: Ventas est. PPSPY | H6: Lanzado hace (meses) | I6: ¿Menos de 10 meses? | J6: ¿En Dropi? | K6: Competidores válidos | L6: Decisión | M6: Notas
B7: =IF(D7="","","P-"&TEXT(ROW()-6,"000")) -> P-001 | C7: L-001 | D7: Producto de ejemplo (borrar) | F7: 29.9 | G7: 1800 | H7: 4 | I7: =IF(H7="","",IF(H7<10,"Sí","No")) -> Sí | J7: Sí | K7: =IF(B7="","",COUNTIFS(Competencia!$B$7:$B$406,B7,Competencia!$G$7:$G$406,"Sí")) -> 1 | L7: Pendiente | M7: Fila de ejemplo
B8: =IF(D8="","","P-"&TEXT(ROW()-6,"000")) | I8: =IF(H8="","",IF(H8<10,"Sí","No")) | K8: =IF(B8="","",COUNTIFS(Competencia!$B$7:$B$406,B8,Competencia!$G$7:$G$406,"Sí"))
B9: =IF(D9="","","P-"&TEXT(ROW()-6,"000")) | I9: =IF(H9="","",IF(H9<10,"Sí","No")) | K9: =IF(B9="","",COUNTIFS(Competencia!$B$7:$B$406,B9,Competencia!$G$7:$G$406,"Sí"))
B10: =IF(D10="","","P-"&TEXT(ROW()-6,"000")) | I10: =IF(H10="","",IF(H10<10,"Sí","No")) | K10: =IF(B10="","",COUNTIFS(Competencia!$B$7:$B$406,B10,Competencia!$G$7:$G$406,"Sí"))
B11: =IF(D11="","","P-"&TEXT(ROW()-6,"000")) | I11: =IF(H11="","",IF(H11<10,"Sí","No")) | K11: =IF(B11="","",COUNTIFS(Competencia!$B$7:$B$406,B11,Competencia!$G$7:$G$406,"Sí"))
B12: =IF(D12="","","P-"&TEXT(ROW()-6,"000")) | I12: =IF(H12="","",IF(H12<10,"Sí","No")) | K12: =IF(B12="","",COUNTIFS(Competencia!$B$7:$B$406,B12,Competencia!$G$7:$G$406,"Sí"))
B13: =IF(D13="","","P-"&TEXT(ROW()-6,"000")) | I13: =IF(H13="","",IF(H13<10,"Sí","No")) | K13: =IF(B13="","",COUNTIFS(Competencia!$B$7:$B$406,B13,Competencia!$G$7:$G$406,"Sí"))
B14: =IF(D14="","","P-"&TEXT(ROW()-6,"000")) | I14: =IF(H14="","",IF(H14<10,"Sí","No")) | K14: =IF(B14="","",COUNTIFS(Competencia!$B$7:$B$406,B14,Competencia!$G$7:$G$406,"Sí"))
B15: =IF(D15="","","P-"&TEXT(ROW()-6,"000")) | I15: =IF(H15="","",IF(H15<10,"Sí","No")) | K15: =IF(B15="","",COUNTIFS(Competencia!$B$7:$B$406,B15,Competencia!$G$7:$G$406,"Sí"))
B16: =IF(D16="","","P-"&TEXT(ROW()-6,"000")) | I16: =IF(H16="","",IF(H16<10,"Sí","No")) | K16: =IF(B16="","",COUNTIFS(Competencia!$B$7:$B$406,B16,Competencia!$G$7:$G$406,"Sí"))
B17: =IF(D17="","","P-"&TEXT(ROW()-6,"000")) | I17: =IF(H17="","",IF(H17<10,"Sí","No")) | K17: =IF(B17="","",COUNTIFS(Competencia!$B$7:$B$406,B17,Competencia!$G$7:$G$406,"Sí"))
B18: =IF(D18="","","P-"&TEXT(ROW()-6,"000")) | I18: =IF(H18="","",IF(H18<10,"Sí","No")) | K18: =IF(B18="","",COUNTIFS(Competencia!$B$7:$B$406,B18,Competencia!$G$7:$G$406,"Sí"))
B19: =IF(D19="","","P-"&TEXT(ROW()-6,"000")) | I19: =IF(H19="","",IF(H19<10,"Sí","No")) | K19: =IF(B19="","",COUNTIFS(Competencia!$B$7:$B$406,B19,Competencia!$G$7:$G$406,"Sí"))
... B406: =IF(D406="","","P-"&TEXT(ROW()-6,"000")) | I406: =IF(H406="","",IF(H406<10,"Sí","No")) | K406: =IF(B406="","",COUNTIFS(Competencia!$B$7:$B$406,B406,Competencia!$G$7:$G$406,"Sí"))

Sheet Competencia
E2: Análisis de competencia
E3: Solo cuentan los competidores con landing activa. WhatsApp y landings apagadas no compiten.
B6: Producto (ID) | C6: Competidor (URL) | D6: Tipo | E6: País | F6: Anuncios activos | G6: ¿Cuenta? | H6: Ángulo que usa | I6: Precio (COP) | J6: Notas
B7: P-001 | C7: competidor-ejemplo.co (EJEMPLO, borrar) | D7: Landing | E7: Colombia | F7: 6 | G7: =IF(D7="","",IF(OR(D7="WhatsApp",D7="Apagado"),"No","Sí")) -> Sí | H7: Alivio rápido en casa | I7: 99900
G8: =IF(D8="","",IF(OR(D8="WhatsApp",D8="Apagado"),"No","Sí"))
G9: =IF(D9="","",IF(OR(D9="WhatsApp",D9="Apagado"),"No","Sí"))
G10: =IF(D10="","",IF(OR(D10="WhatsApp",D10="Apagado"),"No","Sí"))
G11: =IF(D11="","",IF(OR(D11="WhatsApp",D11="Apagado"),"No","Sí"))
G12: =IF(D12="","",IF(OR(D12="WhatsApp",D12="Apagado"),"No","Sí"))
G13: =IF(D13="","",IF(OR(D13="WhatsApp",D13="Apagado"),"No","Sí"))
G14: =IF(D14="","",IF(OR(D14="WhatsApp",D14="Apagado"),"No","Sí"))
G15: =IF(D15="","",IF(OR(D15="WhatsApp",D15="Apagado"),"No","Sí"))
G16: =IF(D16="","",IF(OR(D16="WhatsApp",D16="Apagado"),"No","Sí"))
G17: =IF(D17="","",IF(OR(D17="WhatsApp",D17="Apagado"),"No","Sí"))
G18: =IF(D18="","",IF(OR(D18="WhatsApp",D18="Apagado"),"No","Sí"))
G19: =IF(D19="","",IF(OR(D19="WhatsApp",D19="Apagado"),"No","Sí"))
... G606: =IF(D606="","",IF(OR(D606="WhatsApp",D606="Apagado"),"No","Sí"))

Sheet Finalistas
E2: Filtros de los finalistas
E3: Se llenan solo con los productos que quedaron del banco. Con 8 de 8 en Sí, el producto se valida.
B6: Producto (ID) | C6: Producto | D6: Landing +600 productos | E6: Producto -10 meses | F6: En Dropi | G6: Competidores válidos | H6: Ángulo propio distinto | I6: Margen neto 75% ≥ 25% | J6: Sin réplica, frágil ni salud | K6: Fuera de retail o diferenciado | L6: Filtros en Sí (de 8) | M6: Veredicto | N6: Ángulo de venta / notas
B7: P-001 | C7: =IFERROR(INDEX(Productos!$D$7:$D$406,MATCH(B7,Productos!$B$7:$B$406,0)),"") -> Producto de ejemplo (borrar) | D7: =IFERROR(IF(INDEX(Landings!$G$7:$G$306,MATCH(INDEX(Productos!$C$7:$C$406,MATCH(B7,Productos!$B$7:$B$406,0)),Landings!$B$7:$B$306,0))="Sí","Sí","No"),"") -> Sí | E7: =IFERROR(INDEX(Productos!$I$7:$I$406,MATCH(B7,Productos!$B$7:$B$406,0)),"") -> Sí | F7: =IFERROR(INDEX(Productos!$J$7:$J$406,MATCH(B7,Productos!$B$7:$B$406,0)),"") -> Sí | G7: =IFERROR(INDEX(Productos!$K$7:$K$406,MATCH(B7,Productos!$B$7:$B$406,0)),"") -> 1 | L7: =IF(B7="","",COUNTIF(D7:F7,"Sí")+IF(G7="",0,IF(G7<=5,1,0))+COUNTIF(H7:K7,"Sí")) -> 4 | M7: =IF(B7="","",IF(L7=8,"VALIDAR",IF(L7>=6,"OBSERVAR","DESCARTAR"))) -> DESCARTAR
C8: =IFERROR(INDEX(Productos!$D$7:$D$406,MATCH(B8,Productos!$B$7:$B$406,0)),"") -> 0 | D8: =IFERROR(IF(INDEX(Landings!$G$7:$G$306,MATCH(INDEX(Productos!$C$7:$C$406,MATCH(B8,Productos!$B$7:$B$406,0)),Landings!$B$7:$B$306,0))="Sí","Sí","No"),"") -> No | E8: =IFERROR(INDEX(Productos!$I$7:$I$406,MATCH(B8,Productos!$B$7:$B$406,0)),"") | F8: =IFERROR(INDEX(Productos!$J$7:$J$406,MATCH(B8,Productos!$B$7:$B$406,0)),"") -> 0 | G8: =IFERROR(INDEX(Productos!$K$7:$K$406,MATCH(B8,Productos!$B$7:$B$406,0)),"") | L8: =IF(B8="","",COUNTIF(D8:F8,"Sí")+IF(G8="",0,IF(G8<=5,1,0))+COUNTIF(H8:K8,"Sí")) | M8: =IF(B8="","",IF(L8=8,"VALIDAR",IF(L8>=6,"OBSERVAR","DESCARTAR")))
C9: =IFERROR(INDEX(Productos!$D$7:$D$406,MATCH(B9,Productos!$B$7:$B$406,0)),"") -> 0 | D9: =IFERROR(IF(INDEX(Landings!$G$7:$G$306,MATCH(INDEX(Productos!$C$7:$C$406,MATCH(B9,Productos!$B$7:$B$406,0)),Landings!$B$7:$B$306,0))="Sí","Sí","No"),"") -> No | E9: =IFERROR(INDEX(Productos!$I$7:$I$406,MATCH(B9,Productos!$B$7:$B$406,0)),"") | F9: =IFERROR(INDEX(Productos!$J$7:$J$406,MATCH(B9,Productos!$B$7:$B$406,0)),"") -> 0 | G9: =IFERROR(INDEX(Productos!$K$7:$K$406,MATCH(B9,Productos!$B$7:$B$406,0)),"") | L9: =IF(B9="","",COUNTIF(D9:F9,"Sí")+IF(G9="",0,IF(G9<=5,1,0))+COUNTIF(H9:K9,"Sí")) | M9: =IF(B9="","",IF(L9=8,"VALIDAR",IF(L9>=6,"OBSERVAR","DESCARTAR")))
C10: =IFERROR(INDEX(Productos!$D$7:$D$406,MATCH(B10,Productos!$B$7:$B$406,0)),"") -> 0 | D10: =IFERROR(IF(INDEX(Landings!$G$7:$G$306,MATCH(INDEX(Productos!$C$7:$C$406,MATCH(B10,Productos!$B$7:$B$406,0)),Landings!$B$7:$B$306,0))="Sí","Sí","No"),"") -> No | E10: =IFERROR(INDEX(Productos!$I$7:$I$406,MATCH(B10,Productos!$B$7:$B$406,0)),"") | F10: =IFERROR(INDEX(Productos!$J$7:$J$406,MATCH(B10,Productos!$B$7:$B$406,0)),"") -> 0 | G10: =IFERROR(INDEX(Productos!$K$7:$K$406,MATCH(B10,Productos!$B$7:$B$406,0)),"") | L10: =IF(B10="","",COUNTIF(D10:F10,"Sí")+IF(G10="",0,IF(G10<=5,1,0))+COUNTIF(H10:K10,"Sí")) | M10: =IF(B10="","",IF(L10=8,"VALIDAR",IF(L10>=6,"OBSERVAR","DESCARTAR")))
C11: =IFERROR(INDEX(Productos!$D$7:$D$406,MATCH(B11,Productos!$B$7:$B$406,0)),"") -> 0 | D11: =IFERROR(IF(INDEX(Landings!$G$7:$G$306,MATCH(INDEX(Productos!$C$7:$C$406,MATCH(B11,Productos!$B$7:$B$406,0)),Landings!$B$7:$B$306,0))="Sí","Sí","No"),"") -> No | E11: =IFERROR(INDEX(Productos!$I$7:$I$406,MATCH(B11,Productos!$B$7:$B$406,0)),"") | F11: =IFERROR(INDEX(Productos!$J$7:$J$406,MATCH(B11,Productos!$B$7:$B$406,0)),"") -> 0 | G11: =IFERROR(INDEX(Productos!$K$7:$K$406,MATCH(B11,Productos!$B$7:$B$406,0)),"") | L11: =IF(B11="","",COUNTIF(D11:F11,"Sí")+IF(G11="",0,IF(G11<=5,1,0))+COUNTIF(H11:K11,"Sí")) | M11: =IF(B11="","",IF(L11=8,"VALIDAR",IF(L11>=6,"OBSERVAR","DESCARTAR")))
C12: =IFERROR(INDEX(Productos!$D$7:$D$406,MATCH(B12,Productos!$B$7:$B$406,0)),"") -> 0 | D12: =IFERROR(IF(INDEX(Landings!$G$7:$G$306,MATCH(INDEX(Productos!$C$7:$C$406,MATCH(B12,Productos!$B$7:$B$406,0)),Landings!$B$7:$B$306,0))="Sí","Sí","No"),"") -> No | E12: =IFERROR(INDEX(Productos!$I$7:$I$406,MATCH(B12,Productos!$B$7:$B$406,0)),"") | F12: =IFERROR(INDEX(Productos!$J$7:$J$406,MATCH(B12,Productos!$B$7:$B$406,0)),"") -> 0 | G12: =IFERROR(INDEX(Productos!$K$7:$K$406,MATCH(B12,Productos!$B$7:$B$406,0)),"") | L12: =IF(B12="","",COUNTIF(D12:F12,"Sí")+IF(G12="",0,IF(G12<=5,1,0))+COUNTIF(H12:K12,"Sí")) | M12: =IF(B12="","",IF(L12=8,"VALIDAR",IF(L12>=6,"OBSERVAR","DESCARTAR")))
C13: =IFERROR(INDEX(Productos!$D$7:$D$406,MATCH(B13,Productos!$B$7:$B$406,0)),"") -> 0 | D13: =IFERROR(IF(INDEX(Landings!$G$7:$G$306,MATCH(INDEX(Productos!$C$7:$C$406,MATCH(B13,Productos!$B$7:$B$406,0)),Landings!$B$7:$B$306,0))="Sí","Sí","No"),"") -> No | E13: =IFERROR(INDEX(Productos!$I$7:$I$406,MATCH(B13,Productos!$B$7:$B$406,0)),"") | F13: =IFERROR(INDEX(Productos!$J$7:$J$406,MATCH(B13,Productos!$B$7:$B$406,0)),"") -> 0 | G13: =IFERROR(INDEX(Productos!$K$7:$K$406,MATCH(B13,Productos!$B$7:$B$406,0)),"") | L13: =IF(B13="","",COUNTIF(D13:F13,"Sí")+IF(G13="",0,IF(G13<=5,1,0))+COUNTIF(H13:K13,"Sí")) | M13: =IF(B13="","",IF(L13=8,"VALIDAR",IF(L13>=6,"OBSERVAR","DESCARTAR")))
C14: =IFERROR(INDEX(Productos!$D$7:$D$406,MATCH(B14,Productos!$B$7:$B$406,0)),"") -> 0 | D14: =IFERROR(IF(INDEX(Landings!$G$7:$G$306,MATCH(INDEX(Productos!$C$7:$C$406,MATCH(B14,Productos!$B$7:$B$406,0)),Landings!$B$7:$B$306,0))="Sí","Sí","No"),"") -> No | E14: =IFERROR(INDEX(Productos!$I$7:$I$406,MATCH(B14,Productos!$B$7:$B$406,0)),"") | F14: =IFERROR(INDEX(Productos!$J$7:$J$406,MATCH(B14,Productos!$B$7:$B$406,0)),"") -> 0 | G14: =IFERROR(INDEX(Productos!$K$7:$K$406,MATCH(B14,Productos!$B$7:$B$406,0)),"") | L14: =IF(B14="","",COUNTIF(D14:F14,"Sí")+IF(G14="",0,IF(G14<=5,1,0))+COUNTIF(H14:K14,"Sí")) | M14: =IF(B14="","",IF(L14=8,"VALIDAR",IF(L14>=6,"OBSERVAR","DESCARTAR")))
C15: =IFERROR(INDEX(Productos!$D$7:$D$406,MATCH(B15,Productos!$B$7:$B$406,0)),"") -> 0 | D15: =IFERROR(IF(INDEX(Landings!$G$7:$G$306,MATCH(INDEX(Productos!$C$7:$C$406,MATCH(B15,Productos!$B$7:$B$406,0)),Landings!$B$7:$B$306,0))="Sí","Sí","No"),"") -> No | E15: =IFERROR(INDEX(Productos!$I$7:$I$406,MATCH(B15,Productos!$B$7:$B$406,0)),"") | F15: =IFERROR(INDEX(Productos!$J$7:$J$406,MATCH(B15,Productos!$B$7:$B$406,0)),"") -> 0 | G15: =IFERROR(INDEX(Productos!$K$7:$K$406,MATCH(B15,Productos!$B$7:$B$406,0)),"") | L15: =IF(B15="","",COUNTIF(D15:F15,"Sí")+IF(G15="",0,IF(G15<=5,1,0))+COUNTIF(H15:K15,"Sí")) | M15: =IF(B15="","",IF(L15=8,"VALIDAR",IF(L15>=6,"OBSERVAR","DESCARTAR")))
C16: =IFERROR(INDEX(Productos!$D$7:$D$406,MATCH(B16,Productos!$B$7:$B$406,0)),"") -> 0 | D16: =IFERROR(IF(INDEX(Landings!$G$7:$G$306,MATCH(INDEX(Productos!$C$7:$C$406,MATCH(B16,Productos!$B$7:$B$406,0)),Landings!$B$7:$B$306,0))="Sí","Sí","No"),"") -> No | E16: =IFERROR(INDEX(Productos!$I$7:$I$406,MATCH(B16,Productos!$B$7:$B$406,0)),"") | F16: =IFERROR(INDEX(Productos!$J$7:$J$406,MATCH(B16,Productos!$B$7:$B$406,0)),"") -> 0 | G16: =IFERROR(INDEX(Productos!$K$7:$K$406,MATCH(B16,Productos!$B$7:$B$406,0)),"") | L16: =IF(B16="","",COUNTIF(D16:F16,"Sí")+IF(G16="",0,IF(G16<=5,1,0))+COUNTIF(H16:K16,"Sí")) | M16: =IF(B16="","",IF(L16=8,"VALIDAR",IF(L16>=6,"OBSERVAR","DESCARTAR")))
C17: =IFERROR(INDEX(Productos!$D$7:$D$406,MATCH(B17,Productos!$B$7:$B$406,0)),"") -> 0 | D17: =IFERROR(IF(INDEX(Landings!$G$7:$G$306,MATCH(INDEX(Productos!$C$7:$C$406,MATCH(B17,Productos!$B$7:$B$406,0)),Landings!$B$7:$B$306,0))="Sí","Sí","No"),"") -> No | E17: =IFERROR(INDEX(Productos!$I$7:$I$406,MATCH(B17,Productos!$B$7:$B$406,0)),"") | F17: =IFERROR(INDEX(Productos!$J$7:$J$406,MATCH(B17,Productos!$B$7:$B$406,0)),"") -> 0 | G17: =IFERROR(INDEX(Productos!$K$7:$K$406,MATCH(B17,Productos!$B$7:$B$406,0)),"") | L17: =IF(B17="","",COUNTIF(D17:F17,"Sí")+IF(G17="",0,IF(G17<=5,1,0))+COUNTIF(H17:K17,"Sí")) | M17: =IF(B17="","",IF(L17=8,"VALIDAR",IF(L17>=6,"OBSERVAR","DESCARTAR")))
C18: =IFERROR(INDEX(Productos!$D$7:$D$406,MATCH(B18,Productos!$B$7:$B$406,0)),"") -> 0 | D18: =IFERROR(IF(INDEX(Landings!$G$7:$G$306,MATCH(INDEX(Productos!$C$7:$C$406,MATCH(B18,Productos!$B$7:$B$406,0)),Landings!$B$7:$B$306,0))="Sí","Sí","No"),"") -> No | E18: =IFERROR(INDEX(Productos!$I$7:$I$406,MATCH(B18,Productos!$B$7:$B$406,0)),"") | F18: =IFERROR(INDEX(Productos!$J$7:$J$406,MATCH(B18,Productos!$B$7:$B$406,0)),"") -> 0 | G18: =IFERROR(INDEX(Productos!$K$7:$K$406,MATCH(B18,Productos!$B$7:$B$406,0)),"") | L18: =IF(B18="","",COUNTIF(D18:F18,"Sí")+IF(G18="",0,IF(G18<=5,1,0))+COUNTIF(H18:K18,"Sí")) | M18: =IF(B18="","",IF(L18=8,"VALIDAR",IF(L18>=6,"OBSERVAR","DESCARTAR")))
C19: =IFERROR(INDEX(Productos!$D$7:$D$406,MATCH(B19,Productos!$B$7:$B$406,0)),"") -> 0 | D19: =IFERROR(IF(INDEX(Landings!$G$7:$G$306,MATCH(INDEX(Productos!$C$7:$C$406,MATCH(B19,Productos!$B$7:$B$406,0)),Landings!$B$7:$B$306,0))="Sí","Sí","No"),"") -> No | E19: =IFERROR(INDEX(Productos!$I$7:$I$406,MATCH(B19,Productos!$B$7:$B$406,0)),"") | F19: =IFERROR(INDEX(Productos!$J$7:$J$406,MATCH(B19,Productos!$B$7:$B$406,0)),"") -> 0 | G19: =IFERROR(INDEX(Productos!$K$7:$K$406,MATCH(B19,Productos!$B$7:$B$406,0)),"") | L19: =IF(B19="","",COUNTIF(D19:F19,"Sí")+IF(G19="",0,IF(G19<=5,1,0))+COUNTIF(H19:K19,"Sí")) | M19: =IF(B19="","",IF(L19=8,"VALIDAR",IF(L19>=6,"OBSERVAR","DESCARTAR")))
... C46: =IFERROR(INDEX(Productos!$D$7:$D$406,MATCH(B46,Productos!$B$7:$B$406,0)),"") -> 0 | D46: =IFERROR(IF(INDEX(Landings!$G$7:$G$306,MATCH(INDEX(Productos!$C$7:$C$406,MATCH(B46,Productos!$B$7:$B$406,0)),Landings!$B$7:$B$306,0))="Sí","Sí","No"),"") -> No | E46: =IFERROR(INDEX(Productos!$I$7:$I$406,MATCH(B46,Productos!$B$7:$B$406,0)),"") | F46: =IFERROR(INDEX(Productos!$J$7:$J$406,MATCH(B46,Productos!$B$7:$B$406,0)),"") -> 0 | G46: =IFERROR(INDEX(Productos!$K$7:$K$406,MATCH(B46,Productos!$B$7:$B$406,0)),"") | L46: =IF(B46="","",COUNTIF(D46:F46,"Sí")+IF(G46="",0,IF(G46<=5,1,0))+COUNTIF(H46:K46,"Sí")) | M46: =IF(B46="","",IF(L46=8,"VALIDAR",IF(L46>=6,"OBSERVAR","DESCARTAR")))

Sheet Margen
E2: Calculadora de margen contra entrega
E3: Por cada 100 pedidos despachados. Las celdas en azul son entradas; los valores de abajo son estimaciones de mercado, cámbialos por tus datos reales.
B6: ENTRADAS
B7: Precio de venta (COP) | C7: 89900 | F7: Rango viable 60.000 a 150.000
B8: Costo del producto (COP) | C8: 25000 | F8: Precio Dropi
B9: Flete de ida (COP) | C9: 15000 | F9: Estimación 10.000 a 25.000
B10: Flete de devolución (COP) | C10: 15000 | F10: Estimación
B11: CPA publicidad por pedido (COP) | C11: 20000 | F11: Estimación LatAm 15.000 a 30.000
B12: Comisión plataforma | C12: 0.05 | F12: Estimación 3% a 7%
B15: RESULTADO POR 100 PEDIDOS
B16: Tasa de efectividad | C16: 0.7 | D16: 0.75 | E16: 0.8
B17: Entregados | C17: =100*C16 -> 70 | D17: =100*D16 -> 75 | E17: =100*E16 -> 80
B18: Ingreso | C18: =C17*$C$7 -> 6293000 | D18: =D17*$C$7 -> 6742500 | E18: =E17*$C$7 -> 7192000
B19: Costo producto | C19: =C17*$C$8 -> 1750000 | D19: =D17*$C$8 -> 1875000 | E19: =E17*$C$8 -> 2000000
B20: Flete de ida | C20: =100*$C$9 -> 1500000 | D20: =100*$C$9 -> 1500000 | E20: =100*$C$9 -> 1500000
B21: Flete devolución | C21: =(100-C17)*$C$10 -> 450000 | D21: =(100-D17)*$C$10 -> 375000 | E21: =(100-E17)*$C$10 -> 300000
B22: Publicidad | C22: =100*$C$11 -> 2000000 | D22: =100*$C$11 -> 2000000 | E22: =100*$C$11 -> 2000000
B23: Comisión | C23: =C17*($C$7*$C$12) -> 314650 | D23: =D17*($C$7*$C$12) -> 337125 | E23: =E17*($C$7*$C$12) -> 359600
B24: Utilidad | C24: =C18-C19-C20-C21-C22-C23 -> 278350 | D24: =D18-D19-D20-D21-D22-D23 -> 655375 | E24: =E18-E19-E20-E21-E22-E23 -> 1032400
B25: Margen neto | C25: =IF(C18=0,0,C24/C18) -> 0.044231686 | D25: =IF(D18=0,0,D24/D18) -> 0.097200593 | E25: =IF(E18=0,0,E24/E18) -> 0.14354839
B26: Utilidad por pedido | C26: =C24/100 -> 2783.5 | D26: =D24/100 -> 6553.75 | E26: =E24/100 -> 10324
B27: Veredicto margen | C27: =IF(C25>=0.25,"CUMPLE","NO CUMPLE") -> NO CUMPLE | D27: =IF(D25>=0.25,"CUMPLE","NO CUMPLE") -> NO CUMPLE | E27: =IF(E25>=0.25,"CUMPLE","NO CUMPLE") -> NO CUMPLE
B29: Regla: margen neto a 75% de efectividad por debajo de 25% se descarta. Precio por debajo de 50.000 COP también.

Sheet Guía
E2: Guía del método
E3: Método de búsqueda por mercado internacional
B6: PASO 1 | C6: Biblioteca de Anuncios de Meta: todos los países, todos los anuncios, ordenar por impresiones. Buscar por puntos de dolor.
B7: PASO 2 | C7: Aplicar los filtros a la página: más de 600 productos y productos lanzados hace menos de 10 meses que posiblemente estén en Dropi. Si cumple, se deja la landing en la hoja Landings y se sigue buscando más.
B8: PASO 3 | C8: En PPSPY, sacar unos 20 best winners de cada página y registrarlos en la hoja Productos.
B9: PASO 4 | C9: Revisar a fondo la competencia en la hoja Competencia. Contar solo landings activas. WhatsApp y landings apagadas no compiten. Revisar varias veces, no quedarse con la primera búsqueda.
B10: PASO 5 | C10: Buscar el producto en Dropi. Si no está, buscar otro que resuelva el mismo dolor.
B11: PASO 6 | C11: Pasar los mejores por la hoja Finalistas y calcular el margen en la hoja Margen. Dejar uno o dos que pasen todo.
B12: REGLA | C12: Hasta 5 competidores no descartan el producto si se vende con otro ángulo.
B13: REGLA | C13: Creativo bueno: buenas impresiones, no de los más recientes, con la página desplegando inversión.
B14: REGLA | C14: Tiendas buenas: las de Shanghái son muy buenas. Abrirse a más países.
B15: PAÍSES | C15: Estados Unidos, Brasil, México, Perú, Chile, Argentina, Ecuador, España, Shanghái / China, Reino Unido, Alemania, Francia, Italia, Canadá, Australia, Emiratos Árabes, Turquía, Polonia.
B16: DOLORES | C16: Acné, artritis, pantallas y niños, dolor de espalda, dolor de rodillas, varices, hongos en las uñas, caída del cabello, manchas en la piel, arrugas, ronquidos, mal aliento, sarro dental, mala postura, insomnio, estrés, celulitis, grasa abdominal, juanetes, talones agrietados, pies cansados, hernias, hemorroides, plagas, humedad y moho, olores en casa, orden en cocina, mascotas con pelo en todo, limpieza de auto, jardín con maleza.
B17: NOTA | C17: Este método se usa para descubrir. Las promesas de salud no se pueden usar en anuncios: se vende el alivio o la comodidad, no la cura.

Sheet Listas
B2: Estado landing | C2: Sí / No | D2: Tipo competidor | E2: Decisión producto | F2: País
B3: Dejada | C3: Sí | D3: Landing | E3: Pendiente | F3: Colombia
B4: Analizando | C4: No | D4: WhatsApp | E4: Pasó | F4: Estados Unidos
B5: Descartada | D5: Apagado | E5: Descartado | F5: Brasil
F6: México
F7: Perú
F8: Chile
F9: Argentina
F10: Ecuador
F11: España
F12: Shanghái / China
F13: Reino Unido
F14: Alemania
F15: Francia
F16: Italia
F17: Canadá
... F22: Otro
